setup.py
src/mozilla_django_oidc/__init__.py
src/mozilla_django_oidc/auth.py
src/mozilla_django_oidc/middleware.py
src/mozilla_django_oidc/urls.py
src/mozilla_django_oidc/utils.py
src/mozilla_django_oidc/views.py
src/mozilla_django_oidc/contrib/__init__.py
src/mozilla_django_oidc/contrib/drf.py
src/rest_framework_simplejwt/__init__.py
src/rest_framework_simplejwt/authentication.py
src/rest_framework_simplejwt/backends.py
src/rest_framework_simplejwt/compat.py
src/rest_framework_simplejwt/exceptions.py
src/rest_framework_simplejwt/models.py
src/rest_framework_simplejwt/serializers.py
src/rest_framework_simplejwt/settings.py
src/rest_framework_simplejwt/state.py
src/rest_framework_simplejwt/tokens.py
src/rest_framework_simplejwt/utils.py
src/rest_framework_simplejwt/views.py
src/rest_framework_simplejwt/token_blacklist/__init__.py
src/rest_framework_simplejwt/token_blacklist/admin.py
src/rest_framework_simplejwt/token_blacklist/apps.py
src/rest_framework_simplejwt/token_blacklist/models.py
src/rest_framework_simplejwt/token_blacklist/management/__init__.py
src/rest_framework_simplejwt/token_blacklist/management/commands/__init__.py
src/rest_framework_simplejwt/token_blacklist/management/commands/flushexpiredtokens.py
src/rest_framework_simplejwt/token_blacklist/migrations/0001_initial.py
src/rest_framework_simplejwt/token_blacklist/migrations/0002_outstandingtoken_jti_hex.py
src/rest_framework_simplejwt/token_blacklist/migrations/0003_auto_20171017_2007.py
src/rest_framework_simplejwt/token_blacklist/migrations/0004_auto_20171017_2013.py
src/rest_framework_simplejwt/token_blacklist/migrations/0005_remove_outstandingtoken_jti.py
src/rest_framework_simplejwt/token_blacklist/migrations/0006_auto_20171017_2113.py
src/rest_framework_simplejwt/token_blacklist/migrations/0007_auto_20171017_2214.py
src/rest_framework_simplejwt/token_blacklist/migrations/0008_migrate_to_bigautofield.py
src/rest_framework_simplejwt/token_blacklist/migrations/0010_fix_migrate_to_bigautofield.py
src/rflow_mozilla_simplejwt.egg-info/PKG-INFO
src/rflow_mozilla_simplejwt.egg-info/SOURCES.txt
src/rflow_mozilla_simplejwt.egg-info/dependency_links.txt
src/rflow_mozilla_simplejwt.egg-info/requires.txt
src/rflow_mozilla_simplejwt.egg-info/top_level.txt