Metadata-Version: 2.1
Name: rflow-mozilla-simplejwt
Version: 0.0.1
Summary: rflow-rest-framework-simplejwt
Home-page: UNKNOWN
Author: LI, FUU，SOTA
Author-email: rflowteam@rakuten.com
License: UNKNOWN
Platform: UNKNOWN
